{
    "textures": {
        "particle": "block/cake_side",
        "bottom": "block/cake_bottom",
        "top": "block/cake_top",
        "side": "block/cake_side",
        "inside": "block/cake_inner"
    },
    "elements": [
        {   "from": [ 2, 0, 2 ],
            "to": [ 14, 8, 14 ],
            "faces": {
                "down":  { "uv": [ 2, 2, 14, 14 ], "texture": "#bottom", "cullface": "down" },
                "up":    { "uv": [ 2, 2, 14, 14 ], "texture": "#top" },
                "north": { "uv": [ 2, 8, 14, 16 ], "texture": "#side" },
                "south": { "uv": [ 2, 8, 14, 16 ], "texture": "#side" },
                "west":  { "uv": [ 2, 8, 14, 16 ], "texture": "#inside" },
                "east":  { "uv": [ 2, 8, 14, 16 ], "texture": "#side" }
            }
        }
    ]
}
